similar_documents/__init__.py
similar_documents/cli.py
similar_documents/cmd_utils.py
similar_documents/similar.py
similar_documents/text_converter.py
similar_documents/tokenizer.py
similar_documents-0.1.4.data/scripts/similar-documents
tests/__init__.py
tests/cmd_utils_test.py
tests/similar_test.py
tests/text_converter_test.py
tests/tokonezer_test.py
similar_documents-0.1.4.dist-info/METADATA
similar_documents-0.1.4.dist-info/WHEEL
similar_documents-0.1.4.dist-info/top_level.txt
similar_documents-0.1.4.dist-info/RECORD
