Metadata-Version: 2.1
Name: similar-documents
Version: 0.1.4
Summary: Generate similarity scores for documents from cli
Home-page: UNKNOWN
Author: "Yuichi Tateno"
Author-email: hotchpotch@gmail.com
License: MIT
Project-URL: Source, https://github.com/hotchpotch/similar-documents-cli
Keywords: similar,documents
Platform: UNKNOWN
Requires-Python: >=3.7
Requires-Dist: Markdown
Requires-Dist: markdown-full-yaml-metadata
Requires-Dist: numpy
Requires-Dist: scipy
Requires-Dist: beautifulsoup4
Requires-Dist: scikit-learn
Requires-Dist: fugashi
Requires-Dist: unidic-lite
Requires-Dist: plac
Provides-Extra: testing
Requires-Dist: pytest ; extra == 'testing'
